pirecorder/__init__.py
pirecorder/__version__.py
pirecorder/camconfig.py
pirecorder/convert.py
pirecorder/pirecorder.py
pirecorder/schedule.py
pirecorder/stream.py
pirecorder/videoin.py
pirecorder-3.3.0.dist-info/LICENSE
pirecorder-3.3.0.dist-info/METADATA
pirecorder-3.3.0.dist-info/WHEEL
pirecorder-3.3.0.dist-info/entry_points.txt
pirecorder-3.3.0.dist-info/top_level.txt
pirecorder-3.3.0.dist-info/RECORD
