Metadata-Version: 2.1
Name: pirecorder
Version: 3.3.0
Summary: A python package for controlled and automated image and video recording with the raspberry pi
Home-page: https://github.com/jollejolles
Author: Jolle Jolles
Author-email: j.w.jolles@gmail.com
Maintainer: Jolle Jolles
Maintainer-email: j.w.jolles@gmail.com
License: License :: OSI Approved :: Apache Software License
Download-URL: https://github.com/jollejolles/pirecorder/archive/v3.3.0.tar.gz
Platform: Windows
Platform: Linux
Platform: Mac OS-X
Classifier: Intended Audience :: Science/Research
Classifier: Programming Language :: Python :: 2.7
Classifier: Programming Language :: Python :: 3
Classifier: License :: OSI Approved :: Apache Software License
Classifier: Topic :: Scientific/Engineering :: Visualization
Classifier: Topic :: Scientific/Engineering :: Image Recognition
Classifier: Topic :: Scientific/Engineering :: Information Analysis
Classifier: Topic :: Multimedia :: Video
Classifier: Operating System :: POSIX
Classifier: Operating System :: Unix
Classifier: Operating System :: MacOS
Requires-Dist: pythutils
Requires-Dist: multiprocess
Requires-Dist: python-crontab
Requires-Dist: croniter
Requires-Dist: cron-descriptor
Requires-Dist: pyyaml
Requires-Dist: future
Requires-Dist: numpy (==1.16.5) ; python_version >= "2" and python_version < "3"
Requires-Dist: localconfig (==0.4.2) ; python_version >= "2" and python_version < "3"
Requires-Dist: numpy ; python_version >= "3"
Requires-Dist: localconfig (==1.1.1) ; python_version >= "3"
